Metadata-Version: 2.1
Name: FileMaster
Version: 1.0
Summary: A module to make file handeling a lot easier
Home-page: UNKNOWN
Author: Abhimanyu Pandey
License: UNKNOWN
Platform: UNKNOWN
